{
 "actions": [],
 "allow_rename": 1,
 "autoname": "field:rule_name",
 "creation": "2022-03-29 10:14:04.932422",
 "description": "Define Explicit Conditions",
 "doctype": "DocType",
 "editable_grid": 1,
 "engine": "InnoDB",
 "field_order": [
  "rule_name",
  "disable",
  "for_warehouse",
  "cb_1",
  "rule_description",
  "general_sb",
  "order_created_date_logic",
  "client_logic",
  "program_logic",
  "country_logic",
  "brand_logic",
  "condition_cb_1",
  "order_created_date_condition",
  "client_condition",
  "program_condition",
  "country_condition",
  "brand_condition",
  "value_cb_2",
  "order_created_date_value_1",
  "client_value_1",
  "program_value_1",
  "country_value_1",
  "brand_value_1",
  "value_cb_3",
  "order_created_date_value_2",
  "product_logic_sb",
  "product_logic",
  "selling_price_logic",
  "cost_logic",
  "length_logic",
  "width_logic",
  "height_logic",
  "volume_logic",
  "weight_logic",
  "supplier_logic",
  "product_condition_cb",
  "product_condition",
  "selling_price_condition",
  "cost_condition",
  "length_condition",
  "width_condition",
  "height_condition",
  "volume_condition",
  "weight_condition",
  "supplier_condition",
  "product_value_cb_1",
  "product_value_1",
  "selling_price_value_1",
  "cost_value_1",
  "length_value_1",
  "width_value_1",
  "height_value_1",
  "volume_value_1",
  "weight_value_1",
  "fulfilment_center_supplier",
  "product_value_cb_2",
  "product_blank_value_2",
  "selling_price_value_2",
  "cost_value_2",
  "length_value_2",
  "width_value_2",
  "height_value_2",
  "volume_value_2",
  "weight_value_2",
  "section_break_36",
  "priority",
  "rule_help"
 ],
 "fields": [
  {
   "default": "0",
   "fieldname": "disable",
   "fieldtype": "Check",
   "label": "Disable"
  },
  {
   "fieldname": "for_warehouse",
   "fieldtype": "Link",
   "in_list_view": 1,
   "label": "For Warehouse",
   "options": "Warehouse",
   "reqd": 1
  },
  {
   "default": "0",
   "fieldname": "priority",
   "fieldtype": "Int",
   "label": "Priority"
  },
  {
   "fieldname": "rule_help",
   "fieldtype": "HTML",
   "label": "Fulfilment Center Rule Help"
  },
  {
   "default": "NOT USED",
   "fieldname": "order_created_date_logic",
   "fieldtype": "Select",
   "label": "<b>Order Created Date</b>",
   "options": "\nNOT USED\nAND\nOR"
  },
  {
   "fieldname": "order_created_date_condition",
   "fieldtype": "Select",
   "label": "Order Condition",
   "options": "\n>\n<\nbetween"
  },
  {
   "default": "NOT USED",
   "fieldname": "client_logic",
   "fieldtype": "Select",
   "label": "<b>Client</b>",
   "options": "\nNOT USED\nAND\nOR"
  },
  {
   "fieldname": "client_condition",
   "fieldtype": "Select",
   "label": "Client Condition",
   "options": "\nIN\nNOT IN"
  },
  {
   "default": "NOT USED",
   "fieldname": "program_logic",
   "fieldtype": "Select",
   "label": "<b>Program</b>",
   "options": "\nNOT USED\nAND\nOR"
  },
  {
   "fieldname": "program_condition",
   "fieldtype": "Select",
   "label": "Program Condition",
   "options": "\nIN\nNOT IN"
  },
  {
   "default": "NOT USED",
   "fieldname": "country_logic",
   "fieldtype": "Select",
   "label": "<b>Destination Country</b>",
   "options": "\nNOT USED\nAND\nOR"
  },
  {
   "fieldname": "country_condition",
   "fieldtype": "Select",
   "label": "Country Condition",
   "options": "\nIN\nNOT IN"
  },
  {
   "fieldname": "brand_condition",
   "fieldtype": "Select",
   "label": "Brand Condition",
   "options": "\nIN\nNOT IN"
  },
  {
   "default": "NOT USED",
   "fieldname": "brand_logic",
   "fieldtype": "Select",
   "label": "<b>Brand</b>",
   "options": "\nNOT USED\nAND\nOR"
  },
  {
   "default": "NOT USED",
   "fieldname": "product_logic",
   "fieldtype": "Select",
   "label": "<b>Product Name</b>",
   "options": "\nNOT USED\nAND\nOR"
  },
  {
   "fieldname": "product_condition",
   "fieldtype": "Select",
   "label": "Product Condition",
   "options": "\nIN\nNOT IN"
  },
  {
   "default": "NOT USED",
   "fieldname": "selling_price_logic",
   "fieldtype": "Select",
   "label": "<b>Selling Price</b>",
   "options": "\nNOT USED\nAND\nOR"
  },
  {
   "default": "NOT USED",
   "fieldname": "cost_logic",
   "fieldtype": "Select",
   "label": "<b>Cost</b>",
   "options": "\nNOT USED\nAND\nOR"
  },
  {
   "fieldname": "cost_condition",
   "fieldtype": "Select",
   "label": "Cost Condition",
   "options": "\n>\n<\nbetween"
  },
  {
   "fieldname": "general_sb",
   "fieldtype": "Section Break",
   "label": "Define General Condition"
  },
  {
   "fieldname": "product_logic_sb",
   "fieldtype": "Section Break",
   "label": "Define Product Condtion"
  },
  {
   "fieldname": "section_break_36",
   "fieldtype": "Section Break"
  },
  {
   "fieldname": "condition_cb_1",
   "fieldtype": "Column Break"
  },
  {
   "fieldname": "value_cb_2",
   "fieldtype": "Column Break"
  },
  {
   "fieldname": "value_cb_3",
   "fieldtype": "Column Break"
  },
  {
   "fieldname": "product_condition_cb",
   "fieldtype": "Column Break"
  },
  {
   "fieldname": "product_value_cb_1",
   "fieldtype": "Column Break"
  },
  {
   "fieldname": "product_value_cb_2",
   "fieldtype": "Column Break"
  },
  {
   "default": "NOT USED",
   "fieldname": "length_logic",
   "fieldtype": "Select",
   "label": "<b>Length</b>",
   "options": "\nNOT USED\nAND\nOR"
  },
  {
   "default": "NOT USED",
   "fieldname": "width_logic",
   "fieldtype": "Select",
   "label": "<b>Width</b>",
   "options": "\nNOT USED\nAND\nOR"
  },
  {
   "default": "NOT USED",
   "fieldname": "height_logic",
   "fieldtype": "Select",
   "label": "<b>Height</b>",
   "options": "\nNOT USED\nAND\nOR"
  },
  {
   "default": "NOT USED",
   "fieldname": "volume_logic",
   "fieldtype": "Select",
   "label": "<b>Volume</b>",
   "options": "\nNOT USED\nAND\nOR"
  },
  {
   "default": "NOT USED",
   "fieldname": "weight_logic",
   "fieldtype": "Select",
   "label": "<b>Weight</b>",
   "options": "\nNOT USED\nAND\nOR"
  },
  {
   "fieldname": "length_condition",
   "fieldtype": "Select",
   "label": "Length Condition",
   "options": "\n>\n<\nbetween"
  },
  {
   "fieldname": "width_condition",
   "fieldtype": "Select",
   "label": "Width Condition",
   "options": "\n>\n<\nbetween"
  },
  {
   "fieldname": "height_condition",
   "fieldtype": "Select",
   "label": "Height Condition",
   "options": "\n>\n<\nbetween"
  },
  {
   "fieldname": "volume_condition",
   "fieldtype": "Select",
   "label": "Volume Condition",
   "options": "\n>\n<\nbetween"
  },
  {
   "fieldname": "weight_condition",
   "fieldtype": "Select",
   "label": "Weight Condition",
   "options": "\n>\n<\nbetween"
  },
  {
   "default": "NOT USED",
   "fieldname": "supplier_logic",
   "fieldtype": "Select",
   "label": "<b>Supplier<b></b></b>",
   "options": "\nNOT USED\nAND\nOR"
  },
  {
   "fieldname": "supplier_condition",
   "fieldtype": "Select",
   "label": "Supplier Condition",
   "options": "\nIN\nNOT IN"
  },
  {
   "fieldname": "fulfilment_center_supplier",
   "fieldtype": "Table MultiSelect",
   "label": "Supplier Value",
   "options": "Fulfilment Center Supplier"
  },
  {
   "fieldname": "product_blank_value_2",
   "fieldtype": "Read Only"
  },
  {
   "fieldname": "rule_name",
   "fieldtype": "Data",
   "in_list_view": 1,
   "label": "Rule Name",
   "reqd": 1,
   "unique": 1
  },
  {
   "fieldname": "cb_1",
   "fieldtype": "Column Break"
  },
  {
   "fieldname": "rule_description",
   "fieldtype": "Small Text",
   "label": "Rule Description"
  },
  {
   "fieldname": "order_created_date_value_1",
   "fieldtype": "Date",
   "label": "Order Date Value"
  },
  {
   "fieldname": "client_value_1",
   "fieldtype": "Table MultiSelect",
   "label": "Client Value",
   "options": "Fulfilment Center Customer"
  },
  {
   "fieldname": "program_value_1",
   "fieldtype": "Table MultiSelect",
   "label": "Program Value",
   "options": "Fulfilment Center Project"
  },
  {
   "fieldname": "country_value_1",
   "fieldtype": "Table MultiSelect",
   "label": "Country Value",
   "options": "Fulfilment Center Country"
  },
  {
   "fieldname": "brand_value_1",
   "fieldtype": "Table MultiSelect",
   "label": "Brand Value",
   "options": "Fulfilment Center Brand"
  },
  {
   "fieldname": "order_created_date_value_2",
   "fieldtype": "Date"
  },
  {
   "fieldname": "selling_price_value_1",
   "fieldtype": "Float",
   "label": "Selling Price Value"
  },
  {
   "fieldname": "cost_value_1",
   "fieldtype": "Float",
   "label": "Cost Value"
  },
  {
   "fieldname": "length_value_1",
   "fieldtype": "Float",
   "label": "Length Value"
  },
  {
   "fieldname": "width_value_1",
   "fieldtype": "Float",
   "label": "Width Value"
  },
  {
   "fieldname": "height_value_1",
   "fieldtype": "Float",
   "label": "Height Value"
  },
  {
   "fieldname": "volume_value_1",
   "fieldtype": "Data",
   "label": "Volume Value"
  },
  {
   "fieldname": "weight_value_1",
   "fieldtype": "Data"
  },
  {
   "fieldname": "selling_price_value_2",
   "fieldtype": "Float"
  },
  {
   "fieldname": "cost_value_2",
   "fieldtype": "Float"
  },
  {
   "fieldname": "length_value_2",
   "fieldtype": "Float"
  },
  {
   "fieldname": "width_value_2",
   "fieldtype": "Float"
  },
  {
   "fieldname": "height_value_2",
   "fieldtype": "Float"
  },
  {
   "fieldname": "volume_value_2",
   "fieldtype": "Float"
  },
  {
   "fieldname": "weight_value_2",
   "fieldtype": "Float"
  },
  {
   "fieldname": "product_value_1",
   "fieldtype": "Table MultiSelect",
   "label": "Product Value",
   "options": "Fulfilment Center Item"
  },
  {
   "fieldname": "selling_price_condition",
   "fieldtype": "Select",
   "label": "Selling Price Condtion",
   "options": "\n>\n<\nbetween"
  }
 ],
 "hide_toolbar": 1,
 "index_web_pages_for_search": 1,
 "links": [],
 "modified": "2022-04-14 12:36:33.745519",
 "modified_by": "Administrator",
 "module": "OMS",
 "name": "Fulfilment Center Assignment Rule",
 "owner": "Administrator",
 "permissions": [
  {
   "create": 1,
   "delete": 1,
   "email": 1,
   "export": 1,
   "print": 1,
   "read": 1,
   "report": 1,
   "role": "System Manager",
   "share": 1,
   "write": 1
  },
  {
   "create": 1,
   "delete": 1,
   "email": 1,
   "export": 1,
   "print": 1,
   "read": 1,
   "report": 1,
   "role": "Stock Manager",
   "share": 1,
   "write": 1
  },
  {
   "email": 1,
   "export": 1,
   "print": 1,
   "read": 1,
   "report": 1,
   "role": "Sales User",
   "share": 1
  },
  {
   "email": 1,
   "export": 1,
   "print": 1,
   "read": 1,
   "report": 1,
   "role": "Sales Manager",
   "share": 1
  },
  {
   "create": 1,
   "delete": 1,
   "email": 1,
   "export": 1,
   "print": 1,
   "read": 1,
   "report": 1,
   "role": "Sales Master Manager",
   "share": 1,
   "write": 1
  },
  {
   "email": 1,
   "export": 1,
   "print": 1,
   "read": 1,
   "report": 1,
   "role": "Stock User",
   "share": 1
  }
 ],
 "sort_field": "modified",
 "sort_order": "DESC"
}